sumarity/__init__.py
sumarity/package_data.dat
sumarity/suma.py
sumarity-1.0.0.data/data/sumarity_data/data_file
sumarity-1.0.0.dist-info/LICENSE.txt
sumarity-1.0.0.dist-info/METADATA
sumarity-1.0.0.dist-info/WHEEL
sumarity-1.0.0.dist-info/entry_points.txt
sumarity-1.0.0.dist-info/top_level.txt
sumarity-1.0.0.dist-info/RECORD
