Metadata-Version: 2.1
Name: sumarity
Version: 1.0.0
Summary: A sum function between 2 numbers
Home-page: https://github.com/StevenLudwig/sumarity
Author: Steve Ludwig Beltran 
Author-email: steve.ludwig.jesus@gmail.com
License: UNKNOWN
Project-URL: Bug Reports, https://github.com/StevenLudwig/sumarity/issues
Project-URL: Funding, https://donate.pypi.org
Project-URL: Say Thanks!, https://www.linkedin.com/in/stevebeltran/
Project-URL: Source, https://github.com/StevenLudwig/sumarity
Keywords: sumarity setuptools development
Platform: UNKNOWN
Classifier: Development Status :: 3 - Alpha
Classifier: Intended Audience :: Developers
Classifier: Topic :: Software Development :: Build Tools
Classifier: License :: OSI Approved :: MIT License
Classifier: Programming Language :: Python :: 3
Classifier: Programming Language :: Python :: 3.5
Classifier: Programming Language :: Python :: 3.6
Classifier: Programming Language :: Python :: 3.7
Classifier: Programming Language :: Python :: 3.8
Classifier: Programming Language :: Python :: 3 :: Only
Requires-Python: >=3.5, <4
Requires-Dist: peppercorn
Provides-Extra: dev
Requires-Dist: check-manifest ; extra == 'dev'
Provides-Extra: test
Requires-Dist: coverage ; extra == 'test'
